seqpad/__init__.py
seqpad/__main__.py
seqpad/core/__init__.py
seqpad/tests/__init__.py
seqpad/tests/test_triplets.py
seqpad-1.0.12.dist-info/LICENSE.txt
seqpad-1.0.12.dist-info/METADATA
seqpad-1.0.12.dist-info/WHEEL
seqpad-1.0.12.dist-info/top_level.txt
seqpad-1.0.12.dist-info/RECORD
