Metadata-Version: 2.2
Name: seqpad
Version: 1.0.12
Summary: This project pads nucleotide sequences.
Author-email: Johannes <johannes-programming@mailfence.com>
License: The MIT License (MIT)
Project-URL: Download, https://pypi.org/project/seqpad/#files
Project-URL: Index, https://pypi.org/project/seqpad/
Project-URL: Source, https://github.com/johannes-programming/seqpad/
Project-URL: Website, https://seqpad.johannes-programming.online/
Classifier: Development Status :: 5 - Production/Stable
Classifier: License :: OSI Approved :: MIT License
Classifier: Natural Language :: English
Classifier: Operating System :: OS Independent
Classifier: Programming Language :: Python
Classifier: Programming Language :: Python :: 3
Classifier: Programming Language :: Python :: 3 :: Only
Classifier: Typing :: Typed
Requires-Python: >=3.8
License-File: LICENSE.txt
Requires-Dist: click>=8.1.7
Requires-Dist: preparse>=0.0.5
